miney/__init__.py
miney/callback.py
miney/chat.py
miney/events.py
miney/exceptions.py
miney/helper.py
miney/inventory.py
miney/lua.py
miney/luanti.py
miney/node.py
miney/nodes.py
miney/player.py
miney/point.py
miney/tool.py
miney/vector.py
miney/luanticlient/__init__.py
miney/luanticlient/client.py
miney/luanticlient/command_handler.py
miney/luanticlient/connection.py
miney/luanticlient/constants.py
miney/luanticlient/exceptions.py
miney/luanticlient/protocol.py
miney/luanticlient/srp.py
miney/luanticlient/state.py
miney-0.5.8.dist-info/licenses/LICENSE
miney-0.5.8.dist-info/METADATA
miney-0.5.8.dist-info/WHEEL
miney-0.5.8.dist-info/top_level.txt
miney-0.5.8.dist-info/RECORD
