Metadata-Version: 2.4
Name: miney
Version: 0.5.8
Summary: The python interface to Luanti
Home-page: https://github.com/miney-py/miney
Author: Robert Lieback
Author-email: robertlieback@zetabyte.de
Project-URL: Documentation, https://miney.readthedocs.io
Classifier: Development Status :: 4 - Beta
Classifier: License :: OSI Approved :: GNU General Public License v3 or later (GPLv3+)
Classifier: Programming Language :: Python :: 3
Classifier: Operating System :: OS Independent
Classifier: Topic :: Games/Entertainment
Requires-Python: >=3.6
License-File: LICENSE
Dynamic: author
Dynamic: author-email
Dynamic: classifier
Dynamic: description
Dynamic: description-content-type
Dynamic: home-page
Dynamic: license-file
Dynamic: project-url
Dynamic: requires-python
Dynamic: summary
